confapp/__init__.py
confapp/settings_manager.py
confapp-1.1.11.dist-info/LICENSE
confapp-1.1.11.dist-info/METADATA
confapp-1.1.11.dist-info/WHEEL
confapp-1.1.11.dist-info/top_level.txt
confapp-1.1.11.dist-info/RECORD
