Metadata-Version: 1.1
Name: confapp
Version: 1.1.11
Summary: Python library that implements a singleton object to use as settings system.
Home-page: https://github.com/UmSenhorQualquer/confapp
Author: Ricardo Jorge Vieira Ribeiro
Author-email: ricardojvr@gmail.com
License: UNKNOWN
Platform: UNKNOWN
Classifier: Intended Audience :: Developers
Classifier: Operating System :: OS Independent
Classifier: Programming Language :: Python
Classifier: Programming Language :: Python :: 2.7
Classifier: Programming Language :: Python :: 3
